drt_gui/__init__.py
drt_gui/__main__.py
drt_gui/widget.py
drt_gui-0.0.2.dist-info/LICENSE
drt_gui-0.0.2.dist-info/METADATA
drt_gui-0.0.2.dist-info/WHEEL
drt_gui-0.0.2.dist-info/top_level.txt
drt_gui-0.0.2.dist-info/RECORD
