Metadata-Version: 2.1
Name: drt-gui
Version: 0.0.2
Summary: GUI for photo restoration app
Home-page: https://github.com/dimiaa/drt-gui
Author: Dmitry Trokhachev
Author-email: dimiaa573@gmail.com
Project-URL: Bug Tracker, https://github.com/dimiaa/drt-gui/issues
Classifier: Programming Language :: Python :: 3
Classifier: License :: OSI Approved :: BSD License
Classifier: Operating System :: OS Independent
Requires-Python: >=3.6,<3.11
License-File: LICENSE
Requires-Dist: numpy
Requires-Dist: PySide2
Requires-Dist: shiboken2
Requires-Dist: drt-telea
Requires-Dist: drt-unet
